{
	"configurations" : 
	[
		{
			"directories" : 
			[
				{
					"build" : ".",
					"jsonFile" : "directory-.-Debug-f5ebdc15457944623624.json",
					"minimumCMakeVersion" : 
					{
						"string" : "3.21"
					},
					"projectIndex" : 0,
					"source" : ".",
					"targetIndexes" : 
					[
						0
					]
				}
			],
			"name" : "Debug",
			"projects" : 
			[
				{
					"directoryIndexes" : 
					[
						0
					],
					"name" : "TheSnowCosimo",
					"targetIndexes" : 
					[
						0
					]
				}
			],
			"targets" : 
			[
				{
					"directoryIndex" : 0,
					"id" : "TheSnowCosimo::@6890427a1f51a3e7e1df",
					"jsonFile" : "target-TheSnowCosimo-Debug-d74e6ffd90fb6133de45.json",
					"name" : "TheSnowCosimo",
					"projectIndex" : 0
				}
			]
		}
	],
	"kind" : "codemodel",
	"paths" : 
	{
		"build" : "/home/bitrey/TheSnowCosimo/build",
		"source" : "/home/bitrey/TheSnowCosimo"
	},
	"version" : 
	{
		"major" : 2,
		"minor" : 4
	}
}
